{
  "label": "ح",
  "type": "static",
  "mirrorable": true,
  "captured_at": "2026-05-07T21:46:23.032Z",
  "frame_count": 1,
  "frames": [
    {
      "landmarks": [
        {
          "x": 0,
          "y": 0,
          "z": 0
        },
        {
          "x": -0.5161,
          "y": -0.375,
          "z": 0.3768
        },
        {
          "x": -0.6593,
          "y": -0.6233,
          "z": 0.5736
        },
        {
          "x": -0.716,
          "y": -0.8157,
          "z": 0.6454
        },
        {
          "x": -0.7704,
          "y": -0.9817,
          "z": 0.6855
        },
        {
          "x": -0.3943,
          "y": -0.8721,
          "z": 0.6728
        },
        {
          "x": -0.7063,
          "y": -1.0126,
          "z": 0.6074
        },
        {
          "x": -1.0093,
          "y": -0.9893,
          "z": 0.4385
        },
        {
          "x": -1.2978,
          "y": -0.9583,
          "z": 0.3222
        },
        {
          "x": -0.2789,
          "y": -0.8664,
          "z": 0.4143
        },
        {
          "x": -0.6833,
          "y": -1.0195,
          "z": 0.3053
        },
        {
          "x": -1.0318,
          "y": -0.9706,
          "z": 0.0294
        },
        {
          "x": -1.2949,
          "y": -0.9272,
          "z": -0.1586
        },
        {
          "x": -0.1503,
          "y": -0.8394,
          "z": 0.1491
        },
        {
          "x": -0.5605,
          "y": -0.9936,
          "z": -0.0176
        },
        {
          "x": -0.9546,
          "y": -0.9418,
          "z": -0.2887
        },
        {
          "x": -1.223,
          "y": -0.8661,
          "z": -0.4522
        },
        {
          "x": -0.0165,
          "y": -0.8155,
          "z": -0.0814
        },
        {
          "x": -0.4228,
          "y": -0.9025,
          "z": -0.2363
        },
        {
          "x": -0.7469,
          "y": -0.8577,
          "z": -0.3836
        },
        {
          "x": -0.9772,
          "y": -0.8078,
          "z": -0.48
        }
      ]
    }
  ]
}