{
  "label": "خ",
  "type": "static",
  "mirrorable": true,
  "captured_at": "2026-05-07T22:09:05.377Z",
  "frame_count": 1,
  "frames": [
    {
      "landmarks": [
        {
          "x": 0,
          "y": 0,
          "z": 0
        },
        {
          "x": 0.5835,
          "y": -0.3262,
          "z": 0.1726
        },
        {
          "x": 0.6986,
          "y": -0.6728,
          "z": 0.1948
        },
        {
          "x": 0.7139,
          "y": -0.9408,
          "z": 0.1326
        },
        {
          "x": 0.6502,
          "y": -1.1152,
          "z": 0.0699
        },
        {
          "x": 0.3079,
          "y": -0.9812,
          "z": 0.2899
        },
        {
          "x": 0.784,
          "y": -1.0313,
          "z": 0.0975
        },
        {
          "x": 1.1332,
          "y": -0.92,
          "z": -0.0914
        },
        {
          "x": 1.4098,
          "y": -0.8251,
          "z": -0.2181
        },
        {
          "x": 0.1761,
          "y": -0.9808,
          "z": 0.084
        },
        {
          "x": 0.7678,
          "y": -1.01,
          "z": -0.1354
        },
        {
          "x": 1.1882,
          "y": -0.8875,
          "z": -0.3017
        },
        {
          "x": 1.5157,
          "y": -0.7649,
          "z": -0.403
        },
        {
          "x": 0.0958,
          "y": -0.9455,
          "z": -0.1458
        },
        {
          "x": 0.7251,
          "y": -0.9616,
          "z": -0.3634
        },
        {
          "x": 1.1375,
          "y": -0.8292,
          "z": -0.4681
        },
        {
          "x": 1.4284,
          "y": -0.6997,
          "z": -0.511
        },
        {
          "x": 0.0777,
          "y": -0.8693,
          "z": -0.3713
        },
        {
          "x": 0.5925,
          "y": -0.8843,
          "z": -0.5245
        },
        {
          "x": 0.9188,
          "y": -0.8125,
          "z": -0.5882
        },
        {
          "x": 1.1937,
          "y": -0.7381,
          "z": -0.6213
        }
      ]
    }
  ]
}