{
  "label": "د",
  "type": "static",
  "mirrorable": true,
  "captured_at": "2026-05-07T22:30:11.327Z",
  "frame_count": 1,
  "frames": [
    {
      "landmarks": [
        {
          "x": 0,
          "y": 0,
          "z": 0
        },
        {
          "x": 0.4077,
          "y": -0.1557,
          "z": -0.0682
        },
        {
          "x": 0.7705,
          "y": -0.4238,
          "z": -0.2199
        },
        {
          "x": 1.1447,
          "y": -0.5428,
          "z": -0.4059
        },
        {
          "x": 1.4924,
          "y": -0.574,
          "z": -0.5802
        },
        {
          "x": 0.5207,
          "y": -0.9032,
          "z": -0.2173
        },
        {
          "x": 0.7313,
          "y": -1.203,
          "z": -0.5147
        },
        {
          "x": 1.0231,
          "y": -1.2667,
          "z": -0.6711
        },
        {
          "x": 1.1959,
          "y": -1.2449,
          "z": -0.7475
        },
        {
          "x": 0.2008,
          "y": -0.9214,
          "z": -0.3326
        },
        {
          "x": 0.6408,
          "y": -1.0221,
          "z": -0.6363
        },
        {
          "x": 0.6488,
          "y": -0.6653,
          "z": -0.6323
        },
        {
          "x": 0.5133,
          "y": -0.5554,
          "z": -0.5665
        },
        {
          "x": -0.0672,
          "y": -0.829,
          "z": -0.4725
        },
        {
          "x": 0.3589,
          "y": -0.8258,
          "z": -0.8002
        },
        {
          "x": 0.4096,
          "y": -0.5112,
          "z": -0.6861
        },
        {
          "x": 0.2325,
          "y": -0.479,
          "z": -0.5396
        },
        {
          "x": -0.3161,
          "y": -0.6712,
          "z": -0.6161
        },
        {
          "x": 0.09,
          "y": -0.6084,
          "z": -0.8094
        },
        {
          "x": 0.1758,
          "y": -0.4072,
          "z": -0.6931
        },
        {
          "x": -0.002,
          "y": -0.4051,
          "z": -0.5703
        }
      ]
    }
  ]
}