{
  "label": "ا",
  "type": "static",
  "mirrorable": true,
  "captured_at": "2026-05-07T21:19:56.709Z",
  "frame_count": 1,
  "frames": [
    {
      "landmarks": [
        {
          "x": 0,
          "y": 0,
          "z": 0
        },
        {
          "x": 0.2744,
          "y": -0.5515,
          "z": -0.3294
        },
        {
          "x": 0.3538,
          "y": -1.1828,
          "z": -0.5092
        },
        {
          "x": 0.3401,
          "y": -1.6821,
          "z": -0.6447
        },
        {
          "x": 0.2632,
          "y": -2.1396,
          "z": -0.7568
        },
        {
          "x": -0.2842,
          "y": -1.0324,
          "z": -0.6213
        },
        {
          "x": 0.7556,
          "y": -0.9439,
          "z": -0.9145
        },
        {
          "x": 0.6662,
          "y": -0.7801,
          "z": -1.0892
        },
        {
          "x": 0.3368,
          "y": -0.781,
          "z": -1.2434
        },
        {
          "x": -0.4648,
          "y": -0.6118,
          "z": -0.64
        },
        {
          "x": 0.7873,
          "y": -0.5207,
          "z": -0.871
        },
        {
          "x": 0.5879,
          "y": -0.427,
          "z": -0.9324
        },
        {
          "x": 0.2482,
          "y": -0.4561,
          "z": -1.0619
        },
        {
          "x": -0.4506,
          "y": -0.2094,
          "z": -0.6784
        },
        {
          "x": 0.7484,
          "y": -0.1461,
          "z": -0.8812
        },
        {
          "x": 0.5609,
          "y": -0.0708,
          "z": -0.8028
        },
        {
          "x": 0.2404,
          "y": -0.1166,
          "z": -0.8096
        },
        {
          "x": -0.3509,
          "y": 0.1412,
          "z": -0.7636
        },
        {
          "x": 0.5958,
          "y": 0.1506,
          "z": -0.9511
        },
        {
          "x": 0.4966,
          "y": 0.1893,
          "z": -0.9443
        },
        {
          "x": 0.2335,
          "y": 0.2087,
          "z": -0.9673
        }
      ]
    }
  ]
}