{
  "label": "ب",
  "type": "static",
  "mirrorable": true,
  "captured_at": "2026-05-07T21:26:28.040Z",
  "frame_count": 1,
  "frames": [
    {
      "landmarks": [
        {
          "x": 0,
          "y": 0,
          "z": 0
        },
        {
          "x": -0.5476,
          "y": -0.1441,
          "z": -0.3244
        },
        {
          "x": -0.9869,
          "y": -0.3941,
          "z": -0.5385
        },
        {
          "x": -0.7785,
          "y": -0.6441,
          "z": -0.7514
        },
        {
          "x": -0.3292,
          "y": -0.7912,
          "z": -0.94
        },
        {
          "x": -1.0445,
          "y": -0.8032,
          "z": -0.2491
        },
        {
          "x": -1.2596,
          "y": -1.1661,
          "z": -0.5667
        },
        {
          "x": -1.3557,
          "y": -1.3634,
          "z": -0.7514
        },
        {
          "x": -1.3946,
          "y": -1.5584,
          "z": -0.8927
        },
        {
          "x": -0.5251,
          "y": -0.8061,
          "z": -0.273
        },
        {
          "x": -0.5444,
          "y": -0.9812,
          "z": -0.6922
        },
        {
          "x": -0.5317,
          "y": -0.6819,
          "z": -0.7509
        },
        {
          "x": -0.516,
          "y": -0.547,
          "z": -0.7187
        },
        {
          "x": -0.0318,
          "y": -0.7601,
          "z": -0.3527
        },
        {
          "x": 0.0119,
          "y": -0.9103,
          "z": -0.7969
        },
        {
          "x": -0.124,
          "y": -0.617,
          "z": -0.6427
        },
        {
          "x": -0.1799,
          "y": -0.4966,
          "z": -0.4481
        },
        {
          "x": 0.4035,
          "y": -0.6707,
          "z": -0.4647
        },
        {
          "x": 0.3998,
          "y": -0.8079,
          "z": -0.762
        },
        {
          "x": 0.2225,
          "y": -0.5883,
          "z": -0.6432
        },
        {
          "x": 0.144,
          "y": -0.4781,
          "z": -0.5022
        }
      ]
    }
  ]
}