{
  "label": "ثمانية",
  "type": "static",
  "mirrorable": true,
  "captured_at": "2026-05-08T16:05:17.030Z",
  "frame_count": 1,
  "frames": [
    {
      "landmarks": [
        {
          "x": 0,
          "y": 0,
          "z": 0
        },
        {
          "x": -0.178,
          "y": -0.2728,
          "z": 0.0046
        },
        {
          "x": -0.2986,
          "y": -0.6191,
          "z": -0.0258
        },
        {
          "x": -0.3884,
          "y": -0.9362,
          "z": -0.0647
        },
        {
          "x": -0.4797,
          "y": -1.13,
          "z": -0.1009
        },
        {
          "x": -0.0882,
          "y": -0.989,
          "z": -0.0501
        },
        {
          "x": -0.1383,
          "y": -1.4359,
          "z": -0.0955
        },
        {
          "x": -0.1583,
          "y": -1.6833,
          "z": -0.1241
        },
        {
          "x": -0.1657,
          "y": -1.879,
          "z": -0.1368
        },
        {
          "x": 0.0393,
          "y": -0.9967,
          "z": -0.0709
        },
        {
          "x": 0.0624,
          "y": -1.4968,
          "z": -0.1006
        },
        {
          "x": 0.0813,
          "y": -1.7962,
          "z": -0.1148
        },
        {
          "x": 0.1075,
          "y": -1.9884,
          "z": -0.1214
        },
        {
          "x": 0.153,
          "y": -0.9177,
          "z": -0.0851
        },
        {
          "x": 0.1765,
          "y": -1.2051,
          "z": -0.0886
        },
        {
          "x": 0.1368,
          "y": -1.1038,
          "z": -0.0593
        },
        {
          "x": 0.1086,
          "y": -0.9574,
          "z": -0.0316
        },
        {
          "x": 0.2524,
          "y": -0.7948,
          "z": -0.1009
        },
        {
          "x": 0.2539,
          "y": -1.014,
          "z": -0.074
        },
        {
          "x": 0.2065,
          "y": -0.9478,
          "z": -0.0235
        },
        {
          "x": 0.183,
          "y": -0.8334,
          "z": 0.02
        }
      ]
    }
  ]
}