{
  "label": "ثلاثة",
  "type": "static",
  "mirrorable": true,
  "captured_at": "2026-05-08T15:20:32.787Z",
  "frame_count": 1,
  "frames": [
    {
      "landmarks": [
        {
          "x": 0,
          "y": 0,
          "z": 0
        },
        {
          "x": 0.1397,
          "y": -0.4332,
          "z": 0.0798
        },
        {
          "x": 0.0967,
          "y": -0.7889,
          "z": 0.0886
        },
        {
          "x": -0.0339,
          "y": -0.9593,
          "z": 0.0935
        },
        {
          "x": -0.173,
          "y": -1.0391,
          "z": 0.0863
        },
        {
          "x": 0.1254,
          "y": -0.9987,
          "z": -0.0596
        },
        {
          "x": 0.1446,
          "y": -1.5716,
          "z": -0.0756
        },
        {
          "x": 0.1433,
          "y": -1.8755,
          "z": -0.0691
        },
        {
          "x": 0.1362,
          "y": -2.1208,
          "z": -0.055
        },
        {
          "x": -0.0456,
          "y": -0.9941,
          "z": -0.0984
        },
        {
          "x": -0.0622,
          "y": -1.6198,
          "z": -0.1166
        },
        {
          "x": -0.0873,
          "y": -1.9687,
          "z": -0.1049
        },
        {
          "x": -0.1147,
          "y": -2.2348,
          "z": -0.0834
        },
        {
          "x": -0.2075,
          "y": -0.9234,
          "z": -0.1186
        },
        {
          "x": -0.2589,
          "y": -1.4491,
          "z": -0.1362
        },
        {
          "x": -0.2713,
          "y": -1.7885,
          "z": -0.1596
        },
        {
          "x": -0.2922,
          "y": -2.0371,
          "z": -0.1707
        },
        {
          "x": -0.3228,
          "y": -0.7882,
          "z": -0.1228
        },
        {
          "x": -0.2619,
          "y": -1.0492,
          "z": -0.1016
        },
        {
          "x": -0.2,
          "y": -0.9622,
          "z": -0.059
        },
        {
          "x": -0.156,
          "y": -0.8241,
          "z": -0.0248
        }
      ]
    }
  ]
}