{
  "label": "ط",
  "type": "static",
  "mirrorable": true,
  "captured_at": "2026-05-08T14:00:05.239Z",
  "frame_count": 1,
  "frames": [
    {
      "landmarks": [
        {
          "x": 0,
          "y": 0,
          "z": 0
        },
        {
          "x": 0.4233,
          "y": -0.3176,
          "z": 0.0084
        },
        {
          "x": 0.6926,
          "y": -0.6226,
          "z": -0.1029
        },
        {
          "x": 1.0178,
          "y": -0.7735,
          "z": -0.2613
        },
        {
          "x": 1.3392,
          "y": -0.877,
          "z": -0.4046
        },
        {
          "x": 0.1695,
          "y": -0.9986,
          "z": -0.125
        },
        {
          "x": 0.5071,
          "y": -1.2853,
          "z": -0.3217
        },
        {
          "x": 0.6978,
          "y": -1.4652,
          "z": -0.4448
        },
        {
          "x": 0.852,
          "y": -1.6316,
          "z": -0.5301
        },
        {
          "x": 0.006,
          "y": -0.9642,
          "z": -0.2652
        },
        {
          "x": 0.7086,
          "y": -1.081,
          "z": -0.5029
        },
        {
          "x": 1.0797,
          "y": -0.9842,
          "z": -0.5619
        },
        {
          "x": 1.3036,
          "y": -0.9339,
          "z": -0.5795
        },
        {
          "x": -0.0846,
          "y": -0.8573,
          "z": -0.4142
        },
        {
          "x": 0.612,
          "y": -0.8532,
          "z": -0.6342
        },
        {
          "x": 0.6259,
          "y": -0.6236,
          "z": -0.5586
        },
        {
          "x": 0.503,
          "y": -0.5135,
          "z": -0.463
        },
        {
          "x": -0.0915,
          "y": -0.6944,
          "z": -0.5725
        },
        {
          "x": 0.4529,
          "y": -0.7448,
          "z": -0.6966
        },
        {
          "x": 0.5235,
          "y": -0.588,
          "z": -0.6121
        },
        {
          "x": 0.4343,
          "y": -0.4921,
          "z": -0.5244
        }
      ]
    }
  ]
}