{
  "label": "ر",
  "type": "static",
  "mirrorable": true,
  "captured_at": "2026-05-08T13:33:49.012Z",
  "frame_count": 1,
  "frames": [
    {
      "landmarks": [
        {
          "x": 0,
          "y": 0,
          "z": 0
        },
        {
          "x": 0.3543,
          "y": -0.2988,
          "z": 0.3218
        },
        {
          "x": 0.6013,
          "y": -0.591,
          "z": 0.347
        },
        {
          "x": 0.9063,
          "y": -0.7725,
          "z": 0.2738
        },
        {
          "x": 1.0854,
          "y": -0.8804,
          "z": 0.2043
        },
        {
          "x": 0.0957,
          "y": -1.0111,
          "z": 0.2257
        },
        {
          "x": 0.3117,
          "y": -1.3917,
          "z": 0.194
        },
        {
          "x": 0.6049,
          "y": -1.4961,
          "z": 0.1899
        },
        {
          "x": 0.8265,
          "y": -1.5199,
          "z": 0.1932
        },
        {
          "x": 0.1066,
          "y": -0.9943,
          "z": -0.01
        },
        {
          "x": 0.8379,
          "y": -1.1374,
          "z": -0.0661
        },
        {
          "x": 0.8882,
          "y": -0.9041,
          "z": -0.02
        },
        {
          "x": 0.7468,
          "y": -0.7726,
          "z": 0.0412
        },
        {
          "x": 0.2122,
          "y": -0.9073,
          "z": -0.2279
        },
        {
          "x": 0.9434,
          "y": -0.921,
          "z": -0.2237
        },
        {
          "x": 0.9173,
          "y": -0.6917,
          "z": -0.1139
        },
        {
          "x": 0.733,
          "y": -0.5787,
          "z": -0.0434
        },
        {
          "x": 0.3787,
          "y": -0.7765,
          "z": -0.4291
        },
        {
          "x": 0.948,
          "y": -0.7034,
          "z": -0.3639
        },
        {
          "x": 0.9103,
          "y": -0.5228,
          "z": -0.2622
        },
        {
          "x": 0.7321,
          "y": -0.4424,
          "z": -0.2004
        }
      ]
    }
  ]
}