{
  "label": "ظ",
  "type": "static",
  "mirrorable": true,
  "captured_at": "2026-05-08T14:03:46.014Z",
  "frame_count": 1,
  "frames": [
    {
      "landmarks": [
        {
          "x": 0,
          "y": 0,
          "z": 0
        },
        {
          "x": 0.5675,
          "y": -0.2888,
          "z": 0.0002
        },
        {
          "x": 0.816,
          "y": -0.6799,
          "z": -0.0389
        },
        {
          "x": 0.9738,
          "y": -0.963,
          "z": -0.1313
        },
        {
          "x": 1.1628,
          "y": -1.1721,
          "z": -0.2048
        },
        {
          "x": 0.3835,
          "y": -0.9764,
          "z": 0.0547
        },
        {
          "x": 0.4555,
          "y": -1.3938,
          "z": -0.0717
        },
        {
          "x": 0.5477,
          "y": -1.6201,
          "z": -0.1649
        },
        {
          "x": 0.6708,
          "y": -1.8199,
          "z": -0.2417
        },
        {
          "x": 0.1959,
          "y": -0.9781,
          "z": -0.0698
        },
        {
          "x": 0.6976,
          "y": -1.1219,
          "z": -0.301
        },
        {
          "x": 0.9988,
          "y": -0.8562,
          "z": -0.3964
        },
        {
          "x": 1.1369,
          "y": -0.648,
          "z": -0.424
        },
        {
          "x": 0.0358,
          "y": -0.9452,
          "z": -0.2099
        },
        {
          "x": 0.5838,
          "y": -1.0418,
          "z": -0.4656
        },
        {
          "x": 0.598,
          "y": -0.7482,
          "z": -0.4287
        },
        {
          "x": 0.466,
          "y": -0.5677,
          "z": -0.3389
        },
        {
          "x": -0.0733,
          "y": -0.875,
          "z": -0.3548
        },
        {
          "x": 0.3989,
          "y": -0.9633,
          "z": -0.5344
        },
        {
          "x": 0.4592,
          "y": -0.7451,
          "z": -0.4809
        },
        {
          "x": 0.3551,
          "y": -0.5921,
          "z": -0.3999
        }
      ]
    }
  ]
}