{
  "label": "ع",
  "type": "static",
  "mirrorable": true,
  "captured_at": "2026-05-08T14:10:12.013Z",
  "frame_count": 1,
  "frames": [
    {
      "landmarks": [
        {
          "x": 0,
          "y": 0,
          "z": 0
        },
        {
          "x": 0.1907,
          "y": -0.386,
          "z": 0.249
        },
        {
          "x": 0.4995,
          "y": -0.5385,
          "z": 0.3985
        },
        {
          "x": 0.7969,
          "y": -0.5512,
          "z": 0.576
        },
        {
          "x": 0.9986,
          "y": -0.5099,
          "z": 0.7961
        },
        {
          "x": 0.8465,
          "y": -0.5555,
          "z": -0.094
        },
        {
          "x": 1.3252,
          "y": -0.6449,
          "z": -0.0688
        },
        {
          "x": 1.593,
          "y": -0.678,
          "z": -0.0254
        },
        {
          "x": 1.8005,
          "y": -0.6908,
          "z": 0.0091
        },
        {
          "x": 0.9364,
          "y": -0.3474,
          "z": -0.0499
        },
        {
          "x": 1.4818,
          "y": -0.4754,
          "z": -0.0403
        },
        {
          "x": 1.7783,
          "y": -0.5465,
          "z": 0.0608
        },
        {
          "x": 2.0062,
          "y": -0.5995,
          "z": 0.1325
        },
        {
          "x": 0.9684,
          "y": -0.1686,
          "z": 0.063
        },
        {
          "x": 1.3952,
          "y": -0.2777,
          "z": 0.3166
        },
        {
          "x": 1.3496,
          "y": -0.3529,
          "z": 0.6713
        },
        {
          "x": 1.2815,
          "y": -0.3798,
          "z": 0.8864
        },
        {
          "x": 0.9542,
          "y": 0.0043,
          "z": 0.1843
        },
        {
          "x": 1.1493,
          "y": -0.1313,
          "z": 0.4788
        },
        {
          "x": 1.1093,
          "y": -0.203,
          "z": 0.7289
        },
        {
          "x": 1.0626,
          "y": -0.2237,
          "z": 0.9037
        }
      ]
    }
  ]
}