{
  "label": "س",
  "type": "static",
  "mirrorable": true,
  "captured_at": "2026-05-08T13:46:32.110Z",
  "frame_count": 1,
  "frames": [
    {
      "landmarks": [
        {
          "x": 0,
          "y": 0,
          "z": 0
        },
        {
          "x": 0.4884,
          "y": -0.219,
          "z": -0.2428
        },
        {
          "x": 0.7424,
          "y": -0.5329,
          "z": -0.3298
        },
        {
          "x": 0.7957,
          "y": -0.8115,
          "z": -0.4071
        },
        {
          "x": 0.6607,
          "y": -1.0476,
          "z": -0.488
        },
        {
          "x": 0.4392,
          "y": -0.9654,
          "z": -0.0373
        },
        {
          "x": 0.4571,
          "y": -1.3556,
          "z": -0.14
        },
        {
          "x": 0.44,
          "y": -1.59,
          "z": -0.2788
        },
        {
          "x": 0.3895,
          "y": -1.7977,
          "z": -0.3916
        },
        {
          "x": 0.1583,
          "y": -0.9868,
          "z": -0.0345
        },
        {
          "x": 0.1888,
          "y": -1.4229,
          "z": -0.1147
        },
        {
          "x": 0.1866,
          "y": -1.7125,
          "z": -0.2623
        },
        {
          "x": 0.1608,
          "y": -1.9528,
          "z": -0.3909
        },
        {
          "x": -0.0948,
          "y": -0.9459,
          "z": -0.0777
        },
        {
          "x": -0.0794,
          "y": -1.3489,
          "z": -0.1695
        },
        {
          "x": -0.048,
          "y": -1.607,
          "z": -0.3152
        },
        {
          "x": -0.025,
          "y": -1.8277,
          "z": -0.4342
        },
        {
          "x": -0.33,
          "y": -0.8654,
          "z": -0.1517
        },
        {
          "x": -0.3149,
          "y": -1.1861,
          "z": -0.2519
        },
        {
          "x": -0.2882,
          "y": -1.4004,
          "z": -0.3517
        },
        {
          "x": -0.2431,
          "y": -1.599,
          "z": -0.4427
        }
      ]
    }
  ]
}