{
  "label": "عشرة",
  "type": "static",
  "mirrorable": true,
  "captured_at": "2026-05-08T15:52:05.862Z",
  "frame_count": 1,
  "frames": [
    {
      "landmarks": [
        {
          "x": 0,
          "y": 0,
          "z": 0
        },
        {
          "x": 0.0061,
          "y": -0.5103,
          "z": 0.0842
        },
        {
          "x": -0.1368,
          "y": -0.8165,
          "z": 0.1102
        },
        {
          "x": -0.2827,
          "y": -0.9257,
          "z": 0.1179
        },
        {
          "x": -0.4026,
          "y": -0.8767,
          "z": 0.1179
        },
        {
          "x": -0.2582,
          "y": -1.1043,
          "z": 0.0281
        },
        {
          "x": -0.495,
          "y": -1.4094,
          "z": 0.0444
        },
        {
          "x": -0.6363,
          "y": -1.563,
          "z": 0.0566
        },
        {
          "x": -0.7532,
          "y": -1.6723,
          "z": 0.0582
        },
        {
          "x": -0.373,
          "y": -0.9277,
          "z": -0.0133
        },
        {
          "x": -0.4904,
          "y": -0.9777,
          "z": 0.0194
        },
        {
          "x": -0.4276,
          "y": -0.869,
          "z": 0.0531
        },
        {
          "x": -0.3521,
          "y": -0.8007,
          "z": 0.0643
        },
        {
          "x": -0.445,
          "y": -0.6904,
          "z": -0.0418
        },
        {
          "x": -0.4986,
          "y": -0.7359,
          "z": 0.0199
        },
        {
          "x": -0.4455,
          "y": -0.6496,
          "z": 0.0658
        },
        {
          "x": -0.3904,
          "y": -0.5782,
          "z": 0.072
        },
        {
          "x": -0.4975,
          "y": -0.444,
          "z": -0.0684
        },
        {
          "x": -0.5113,
          "y": -0.5062,
          "z": -0.0046
        },
        {
          "x": -0.4526,
          "y": -0.4332,
          "z": 0.0434
        },
        {
          "x": -0.3985,
          "y": -0.3776,
          "z": 0.0674
        }
      ]
    }
  ]
}