{
  "label": "سبعة",
  "type": "static",
  "mirrorable": true,
  "captured_at": "2026-05-08T16:04:15.153Z",
  "frame_count": 1,
  "frames": [
    {
      "landmarks": [
        {
          "x": 0,
          "y": 0,
          "z": 0
        },
        {
          "x": -0.1933,
          "y": -0.2508,
          "z": 0.0195
        },
        {
          "x": -0.3378,
          "y": -0.6228,
          "z": -0.0056
        },
        {
          "x": -0.4515,
          "y": -0.9709,
          "z": -0.0337
        },
        {
          "x": -0.5709,
          "y": -1.156,
          "z": -0.0649
        },
        {
          "x": -0.1842,
          "y": -0.9709,
          "z": -0.096
        },
        {
          "x": -0.1842,
          "y": -1.5215,
          "z": -0.1332
        },
        {
          "x": -0.1765,
          "y": -1.8393,
          "z": -0.144
        },
        {
          "x": -0.1726,
          "y": -2.0833,
          "z": -0.1466
        },
        {
          "x": -0.0437,
          "y": -0.9934,
          "z": -0.106
        },
        {
          "x": 0.035,
          "y": -1.2097,
          "z": -0.1042
        },
        {
          "x": 0.0238,
          "y": -1.0444,
          "z": -0.0549
        },
        {
          "x": -0.0065,
          "y": -0.8935,
          "z": -0.0268
        },
        {
          "x": 0.1016,
          "y": -0.9134,
          "z": -0.1064
        },
        {
          "x": 0.1349,
          "y": -1.0786,
          "z": -0.1099
        },
        {
          "x": 0.1263,
          "y": -0.9463,
          "z": -0.0567
        },
        {
          "x": 0.1047,
          "y": -0.8183,
          "z": -0.0251
        },
        {
          "x": 0.2392,
          "y": -0.8191,
          "z": -0.099
        },
        {
          "x": 0.2469,
          "y": -1.0055,
          "z": -0.0679
        },
        {
          "x": 0.2296,
          "y": -0.8715,
          "z": 0.0052
        },
        {
          "x": 0.2115,
          "y": -0.7408,
          "z": 0.0558
        }
      ]
    }
  ]
}