{
  "label": "ض",
  "type": "static",
  "mirrorable": true,
  "captured_at": "2026-05-08T13:56:42.583Z",
  "frame_count": 1,
  "frames": [
    {
      "landmarks": [
        {
          "x": 0,
          "y": 0,
          "z": 0
        },
        {
          "x": 0.2599,
          "y": -0.1571,
          "z": -0.1709
        },
        {
          "x": 0.5361,
          "y": -0.4973,
          "z": -0.2512
        },
        {
          "x": 0.7423,
          "y": -0.8079,
          "z": -0.3084
        },
        {
          "x": 0.8972,
          "y": -1.0171,
          "z": -0.3325
        },
        {
          "x": 0.2985,
          "y": -0.9897,
          "z": -0.1528
        },
        {
          "x": 0.2515,
          "y": -1.261,
          "z": -0.2838
        },
        {
          "x": 0.2508,
          "y": -0.9093,
          "z": -0.3171
        },
        {
          "x": 0.2717,
          "y": -0.7837,
          "z": -0.3228
        },
        {
          "x": 0.1,
          "y": -0.9871,
          "z": -0.1251
        },
        {
          "x": 0.0398,
          "y": -1.2336,
          "z": -0.2495
        },
        {
          "x": 0.0752,
          "y": -0.8116,
          "z": -0.2402
        },
        {
          "x": 0.1219,
          "y": -0.7763,
          "z": -0.2179
        },
        {
          "x": -0.0782,
          "y": -0.9164,
          "z": -0.1237
        },
        {
          "x": -0.1304,
          "y": -1.1437,
          "z": -0.2604
        },
        {
          "x": -0.0731,
          "y": -0.7799,
          "z": -0.1978
        },
        {
          "x": -0.0194,
          "y": -0.7272,
          "z": -0.1345
        },
        {
          "x": -0.2423,
          "y": -0.8178,
          "z": -0.136
        },
        {
          "x": -0.2955,
          "y": -0.9927,
          "z": -0.2187
        },
        {
          "x": -0.2209,
          "y": -0.7652,
          "z": -0.1782
        },
        {
          "x": -0.1666,
          "y": -0.6822,
          "z": -0.1337
        }
      ]
    }
  ]
}