{
  "label": "ق",
  "type": "static",
  "mirrorable": true,
  "captured_at": "2026-05-08T14:21:29.564Z",
  "frame_count": 1,
  "frames": [
    {
      "landmarks": [
        {
          "x": 0,
          "y": 0,
          "z": 0
        },
        {
          "x": 0.5612,
          "y": -0.1644,
          "z": -0.3002
        },
        {
          "x": 0.9976,
          "y": -0.4778,
          "z": -0.4118
        },
        {
          "x": 0.9122,
          "y": -0.7934,
          "z": -0.5237
        },
        {
          "x": 0.5004,
          "y": -0.9562,
          "z": -0.586
        },
        {
          "x": 0.5928,
          "y": -0.9721,
          "z": -0.1371
        },
        {
          "x": 0.6297,
          "y": -1.38,
          "z": -0.4882
        },
        {
          "x": 0.5083,
          "y": -1.329,
          "z": -0.7093
        },
        {
          "x": 0.3808,
          "y": -1.1039,
          "z": -0.7891
        },
        {
          "x": 0.0958,
          "y": -0.984,
          "z": -0.15
        },
        {
          "x": -0.0811,
          "y": -1.4431,
          "z": -0.4842
        },
        {
          "x": -0.0252,
          "y": -1.3764,
          "z": -0.6416
        },
        {
          "x": 0.0868,
          "y": -1.1829,
          "z": -0.6729
        },
        {
          "x": -0.3006,
          "y": -0.8961,
          "z": -0.2256
        },
        {
          "x": -0.4027,
          "y": -1.006,
          "z": -0.5922
        },
        {
          "x": -0.1697,
          "y": -0.7809,
          "z": -0.6985
        },
        {
          "x": 0.0238,
          "y": -0.5654,
          "z": -0.6765
        },
        {
          "x": -0.6197,
          "y": -0.7406,
          "z": -0.3327
        },
        {
          "x": -0.6085,
          "y": -0.7449,
          "z": -0.5949
        },
        {
          "x": -0.3959,
          "y": -0.59,
          "z": -0.6586
        },
        {
          "x": -0.2007,
          "y": -0.4447,
          "z": -0.6447
        }
      ]
    }
  ]
}