{
  "label": "م",
  "type": "static",
  "mirrorable": true,
  "captured_at": "2026-05-08T14:30:56.011Z",
  "frame_count": 1,
  "frames": [
    {
      "landmarks": [
        {
          "x": 0,
          "y": 0,
          "z": 0
        },
        {
          "x": 0.3772,
          "y": -0.1811,
          "z": -0.3273
        },
        {
          "x": 0.611,
          "y": -0.5139,
          "z": -0.5303
        },
        {
          "x": 0.5676,
          "y": -0.8714,
          "z": -0.7211
        },
        {
          "x": 0.2579,
          "y": -1.0725,
          "z": -0.8642
        },
        {
          "x": 0.489,
          "y": -1.0027,
          "z": -0.1804
        },
        {
          "x": 0.4524,
          "y": -1.2626,
          "z": -0.4736
        },
        {
          "x": 0.4554,
          "y": -1.1596,
          "z": -0.58
        },
        {
          "x": 0.4259,
          "y": -0.9956,
          "z": -0.5831
        },
        {
          "x": 0.11,
          "y": -0.9816,
          "z": -0.156
        },
        {
          "x": 0.0195,
          "y": -1.1673,
          "z": -0.5093
        },
        {
          "x": 0.0873,
          "y": -0.7828,
          "z": -0.5724
        },
        {
          "x": 0.1966,
          "y": -0.6351,
          "z": -0.5142
        },
        {
          "x": -0.2278,
          "y": -0.9117,
          "z": -0.1972
        },
        {
          "x": -0.3597,
          "y": -1.0682,
          "z": -0.5624
        },
        {
          "x": -0.1682,
          "y": -0.7616,
          "z": -0.5877
        },
        {
          "x": -0.0469,
          "y": -0.6016,
          "z": -0.5065
        },
        {
          "x": -0.5518,
          "y": -0.8113,
          "z": -0.2623
        },
        {
          "x": -0.773,
          "y": -1.0909,
          "z": -0.4642
        },
        {
          "x": -0.853,
          "y": -1.2733,
          "z": -0.5082
        },
        {
          "x": -0.9386,
          "y": -1.5092,
          "z": -0.4977
        }
      ]
    }
  ]
}