{
  "label": "ن",
  "type": "static",
  "mirrorable": true,
  "captured_at": "2026-05-08T14:40:23.204Z",
  "frame_count": 1,
  "frames": [
    {
      "landmarks": [
        {
          "x": 0,
          "y": 0,
          "z": 0
        },
        {
          "x": 0.2427,
          "y": -0.4554,
          "z": 0.1449
        },
        {
          "x": 0.1032,
          "y": -0.8485,
          "z": 0.1938
        },
        {
          "x": 0.0232,
          "y": -1.1399,
          "z": 0.1512
        },
        {
          "x": 0.0437,
          "y": -1.3875,
          "z": 0.1123
        },
        {
          "x": -0.4996,
          "y": -0.804,
          "z": 0.4653
        },
        {
          "x": -0.723,
          "y": -1.0683,
          "z": 0.4545
        },
        {
          "x": -0.747,
          "y": -1.2239,
          "z": 0.433
        },
        {
          "x": -0.7837,
          "y": -1.4007,
          "z": 0.4017
        },
        {
          "x": -0.6255,
          "y": -0.7253,
          "z": 0.2875
        },
        {
          "x": -0.4686,
          "y": -1.027,
          "z": 0.1432
        },
        {
          "x": -0.2829,
          "y": -0.8074,
          "z": 0.064
        },
        {
          "x": -0.3643,
          "y": -0.7067,
          "z": 0.0736
        },
        {
          "x": -0.6982,
          "y": -0.63,
          "z": 0.086
        },
        {
          "x": -0.4901,
          "y": -0.928,
          "z": -0.1153
        },
        {
          "x": -0.2886,
          "y": -0.6996,
          "z": -0.1313
        },
        {
          "x": -0.4111,
          "y": -0.6074,
          "z": -0.0725
        },
        {
          "x": -0.774,
          "y": -0.5731,
          "z": -0.1032
        },
        {
          "x": -0.5379,
          "y": -0.7967,
          "z": -0.2369
        },
        {
          "x": -0.3696,
          "y": -0.6883,
          "z": -0.2329
        },
        {
          "x": -0.4614,
          "y": -0.6261,
          "z": -0.1952
        }
      ]
    }
  ]
}