{
  "label": "ن",
  "type": "static",
  "mirrorable": true,
  "captured_at": "2026-05-08T14:40:24.120Z",
  "frame_count": 1,
  "frames": [
    {
      "landmarks": [
        {
          "x": 0,
          "y": 0,
          "z": 0
        },
        {
          "x": 0.2128,
          "y": -0.3892,
          "z": 0.0753
        },
        {
          "x": 0.1756,
          "y": -0.7602,
          "z": 0.0644
        },
        {
          "x": 0.1619,
          "y": -1.0181,
          "z": -0.0009
        },
        {
          "x": 0.188,
          "y": -1.2491,
          "z": -0.0666
        },
        {
          "x": -0.4939,
          "y": -0.8106,
          "z": 0.1285
        },
        {
          "x": -0.7509,
          "y": -1.0446,
          "z": 0.0356
        },
        {
          "x": -0.7877,
          "y": -1.2448,
          "z": -0.0288
        },
        {
          "x": -0.8219,
          "y": -1.4027,
          "z": -0.0717
        },
        {
          "x": -0.6535,
          "y": -0.7569,
          "z": 0.0051
        },
        {
          "x": -0.3029,
          "y": -1.0411,
          "z": -0.1326
        },
        {
          "x": -0.0566,
          "y": -0.8584,
          "z": -0.146
        },
        {
          "x": -0.0625,
          "y": -0.733,
          "z": -0.1045
        },
        {
          "x": -0.6666,
          "y": -0.6569,
          "z": -0.1267
        },
        {
          "x": -0.2453,
          "y": -0.9119,
          "z": -0.2864
        },
        {
          "x": -0.0328,
          "y": -0.7226,
          "z": -0.2144
        },
        {
          "x": -0.1099,
          "y": -0.6033,
          "z": -0.1152
        },
        {
          "x": -0.5973,
          "y": -0.5521,
          "z": -0.254
        },
        {
          "x": -0.2044,
          "y": -0.7593,
          "z": -0.347
        },
        {
          "x": -0.0601,
          "y": -0.6268,
          "z": -0.2633
        },
        {
          "x": -0.1515,
          "y": -0.5216,
          "z": -0.1728
        }
      ]
    }
  ]
}